cytotransform/__init__.py
cytotransform/asinh.py
cytotransform/base.py
cytotransform/hyperlog.py
cytotransform/log.py
cytotransform/logicle.py
cytotransform/logicle_ext/.gitignore
cytotransform/logicle_ext/FastLogicle.cpp
cytotransform/logicle_ext/LICENSE.txt
cytotransform/logicle_ext/Logicle.cpp
cytotransform/logicle_ext/logicle.h
logicle_ext.cpython-311-x86_64-linux-gnu.so
cytotransform-0.2.12.dist-info/LICENSE
cytotransform-0.2.12.dist-info/METADATA
cytotransform-0.2.12.dist-info/WHEEL
cytotransform-0.2.12.dist-info/RECORD
