Metadata-Version: 2.1
Name: cytotransform
Version: 0.2.12
Summary: Rapid transformations for cytometry data
License: MIT
Author: Ross Burton
Author-email: burtonrossj@gmail.com
Requires-Python: >=3.8,<3.12
Classifier: License :: OSI Approved :: MIT License
Classifier: Programming Language :: Python :: 3
Classifier: Programming Language :: Python :: 3.8
Classifier: Programming Language :: Python :: 3.9
Classifier: Programming Language :: Python :: 3.10
Classifier: Programming Language :: Python :: 3.11
Requires-Dist: joblib (>=1.2.0,<2.0.0)
Requires-Dist: matplotlib (>=3.7.1,<4.0.0)
Requires-Dist: numpy (>=1.17.0)
Requires-Dist: pandas (>=1.3.0,<2.0.0)
Requires-Dist: pybind11 (>=2.10.4,<3.0.0)
Requires-Dist: scipy (>=1.10.1,<2.0.0)
Requires-Dist: setuptools (>=67.7.1,<68.0.0)
